{
  "probability": 0.0181,
  "probability_pct": 1.8,
  "will_rain": false,
  "confidence": "Molt Baixa",
  "timestamp": "2026-03-19T18:10:41.530085",
  "conditions": {
    "temperature": "12.0",
    "humidity": 78,
    "pressure": "1018.0",
    "wind_speed": "3.2",
    "wind_dir": "ENE",
    "rain_today": "0.0",
    "solar_radiation": 28
  },
  "radar": {
    "dbz": 0.0,
    "rain_rate_mmh": 0.0,
    "has_echo": false,
    "approaching": false,
    "nearest_echo_km": 30,
    "nearest_echo_compass": null,
    "max_dbz_20km": 0.0,
    "coverage_20km": 0.0,
    "upwind_nearest_echo_km": 30,
    "storm_velocity_kmh": 0.0,
    "storm_eta_min": null
  },
  "sentinel": {
    "station": "Granollers",
    "temp": null,
    "humidity": null,
    "precip": null,
    "raining": 0
  },
  "ensemble": {
    "rain_agreement": 0.0,
    "precip_spread_mm": 0.0,
    "models_rain": 0,
    "total_models": 4
  },
  "aemet": {
    "prob_precip": 0,
    "prob_storm": 0
  },
  "bias": {
    "temp": 0.5999999999999996,
    "humidity": -11.0
  },
  "wind_regime": {
    "level": "850hPa",
    "is_tramuntana": false,
    "is_llevantada": false,
    "is_migjorn": false,
    "is_garbi": false,
    "is_ponent": false,
    "llevantada_strength": 0.0,
    "wind_dir_change_3h": -22.5
  },
  "pressure_levels": {
    "wind_850_dir": 57,
    "wind_850_speed_kmh": 27.3,
    "temp_850": 1.9,
    "temp_500": -20.5,
    "rh_850": 85,
    "rh_700": 74,
    "temp_700": -5.0,
    "vt_index": 22.4,
    "tt_index": 42.54858325857029,
    "li_index": -0.3305770478208885
  },
  "rain_gate_open": false,
  "features_used": 54,
  "threshold": 0.3541666666666667,
  "calibrated": true,
  "raw_probability": 0.115,
  "feature_vector": {
    "hour_sin": -1.0,
    "hour_cos": -1.8369701987210297e-16,
    "month_sin": 1.0,
    "month_cos": 6.123233995736766e-17,
    "pressure_msl": 1018.0125,
    "pressure_change_1h": 0.01694444444444798,
    "pressure_change_3h": -0.41403061224491466,
    "pressure_change_6h": -1.2585526315789366,
    "pressure_accel_3h": 0.37339255560380025,
    "temperature_2m": 12.0625,
    "relative_humidity_2m": 77.25,
    "dew_point": 8.200674970671551,
    "dew_point_depression": 3.8618250293284486,
    "humidity_change_1h": 1.4500000000000028,
    "humidity_change_3h": 1.0459183673469425,
    "vapour_pressure_deficit": null,
    "vpd_change_3h": null,
    "wind_speed_10m": 3.6,
    "wind_u": -2.545584412271571,
    "wind_v": -2.5455844122715714,
    "wind_speed_change_1h": -4.322222222222223,
    "wind_speed_change_3h": -6.085714285714287,
    "is_sea_breeze": 1.0,
    "is_migjorn": 0.0,
    "is_garbi": 0.0,
    "is_ponent": 0.0,
    "llevantada_strength": 0.0,
    "llevantada_moisture": 0.0,
    "garbi_strength": 0.0,
    "wind_dir_change_3h": -22.5,
    "wind_850_speed": 27.3,
    "wind_850_dir": 57.0,
    "temp_850": 1.9,
    "temp_500": -20.5,
    "rh_850": 85.0,
    "rh_700": 74.0,
    "temp_700": -5.0,
    "vt_index": 22.4,
    "tt_index": 42.54858325857029,
    "li_index": -0.3305770478208885,
    "li_unstable": null,
    "wind_shear_speed": null,
    "wind_shear_dir": null,
    "precipitation": 0.0,
    "rain_accum_3h": 0.0,
    "rain_accum_6h": 0.0,
    "rained_last_3h": 0.0,
    "cloud_cover": 99.0,
    "cloud_change_1h": 0.0,
    "cloud_change_3h": null,
    "is_overcast": 1.0,
    "weather_code": 3.0,
    "model_predicts_precip": 0.0,
    "shortwave_radiation": 33.375
  },
  "pressure_change_3h": -0.41403061224491466
}