{
  "probability": 0.1607,
  "probability_pct": 16.1,
  "will_rain": false,
  "rain_category": "sec",
  "confidence": "Molt Baixa",
  "timestamp": "2026-05-03T02:11:15.332590",
  "conditions": {
    "temperature": "16.6",
    "humidity": 79,
    "pressure": "1019.6",
    "wind_speed": "0.0",
    "wind_dir": "N",
    "rain_today": "0.0",
    "solar_radiation": 0
  },
  "radar": {
    "dbz": 0.0,
    "rain_rate_mmh": 0.0,
    "has_echo": false,
    "approaching": false,
    "nearest_echo_km": 40,
    "nearest_echo_compass": null,
    "max_dbz_20km": 0.0,
    "coverage_20km": 0.0,
    "upwind_nearest_echo_km": 40,
    "storm_velocity_kmh": 0.0,
    "storm_eta_min": null,
    "quadrants": {
      "max_dbz_N": 0.0,
      "max_dbz_E": 0.0,
      "max_dbz_S": 0.0,
      "max_dbz_W": 0.0,
      "coverage_N": 0.0,
      "coverage_E": 0.0,
      "coverage_S": 0.0,
      "coverage_W": 0.0
    }
  },
  "sentinel": {
    "station": "Granollers",
    "temp": null,
    "humidity": null,
    "precip": null,
    "raining": 0
  },
  "ensemble": {
    "rain_agreement": 0.25,
    "precip_spread_mm": 3.4,
    "models_rain": 1,
    "total_models": 4
  },
  "aemet": {
    "prob_precip": 0,
    "prob_storm": 0
  },
  "bias": {
    "temp": -2.5000000000000018,
    "humidity": 11.0
  },
  "wind_regime": {
    "level": "850hPa",
    "is_tramuntana": false,
    "is_llevantada": false,
    "is_migjorn": true,
    "is_garbi": false,
    "is_ponent": false,
    "llevantada_strength": 0.0,
    "wind_dir_change_3h": -5.0
  },
  "pressure_levels": {
    "temp_925": 10.4,
    "rh_925": 94,
    "wind_925_speed_kmh": 12.1,
    "wind_925_dir": 174,
    "wind_850_dir": 181,
    "wind_850_speed_kmh": 23.7,
    "temp_850": 8.1,
    "rh_850": 64,
    "rh_700": 89,
    "temp_700": -0.2,
    "temp_500": -16.6,
    "wind_300_speed_kmh": 66.2,
    "wind_300_dir": 248,
    "gph_300": 9350.0,
    "vt_index": 24.700000000000003,
    "tt_index": 43.00259925146168,
    "li_index": -0.6612346444442991
  },
  "sst": {
    "sst_med": 17.6
  },
  "rain_gate_open": true,
  "station_available": true,
  "features_used": 211,
  "threshold": 0.35714285714285715,
  "calibrated": true,
  "raw_probability": 0.132,
  "physical_adjustments": [],
  "feature_vector": {
    "hour_sin": 0.49999999999999994,
    "hour_cos": 0.8660254037844387,
    "month_sin": 0.49999999999999994,
    "month_cos": -0.8660254037844387,
    "hours_since_sunrise": 0.0,
    "pressure_msl": 1019.6200000000001,
    "pressure_change_1h": -0.3319230769229762,
    "pressure_change_3h": -1.1030769230767419,
    "pressure_change_6h": -0.5327272727271293,
    "pressure_accel_3h": -0.4746078431371643,
    "temperature_2m": 16.62,
    "relative_humidity_2m": 79.5,
    "dew_point": 13.056073073265088,
    "dew_point_depression": 3.563926926734913,
    "humidity_change_1h": -1.1923076923076934,
    "humidity_change_3h": -1.4423076923076934,
    "vapour_pressure_deficit": 0.16,
    "vpd_change_3h": -0.03,
    "wind_speed_10m": 0.4800000000000001,
    "wind_u": -0.0,
    "wind_v": -0.4800000000000001,
    "wind_speed_change_1h": 0.01846153846153853,
    "wind_speed_change_3h": -0.966153846153846,
    "is_sea_breeze": 0.0,
    "llevantada_strength": 0.0,
    "llevantada_moisture": 0.0,
    "garbi_strength": 0.0,
    "tramuntana_strength": 0.0,
    "tramuntana_moisture": 0.0,
    "wind_dir_change_3h": -5.0,
    "has_pressure_levels": 1.0,
    "temp_925": 10.4,
    "rh_925": 94.0,
    "wind_925_speed": 12.1,
    "wind_925_dir": 174.0,
    "wind_850_speed": 23.7,
    "wind_850_dir": 181.0,
    "temp_850": 8.1,
    "temp_500": -16.6,
    "rh_850": 64.0,
    "rh_700": 89.0,
    "temp_700": -0.2,
    "rh_700_change_3h": 15.0,
    "rh_700_change_6h": 10.0,
    "temp_850_change_3h": 0.5,
    "wind_300_speed": 66.2,
    "wind_300_dir": 248.0,
    "gph_300": 9350.0,
    "vt_index": 24.700000000000003,
    "tt_index": 43.00259925146168,
    "li_index": -0.6612346444442991,
    "li_unstable": 0.0,
    "k_index": 24.81207807843875,
    "moisture_flux_850": 163.7448210728899,
    "moisture_flux_925": 143.36088419994047,
    "theta_e_deficit": 28.814538895612287,
    "inversion_925": -6.220000000000001,
    "deep_layer_shear": 42.5,
    "bulk_richardson": 0.0,
    "jet_speed_300": 66.2,
    "wind_shear_speed": 23.22,
    "wind_shear_dir": -179.0,
    "precipitation": 0.0,
    "rain_accum_3h": 0.0,
    "rain_accum_6h": 0.0,
    "rained_last_3h": 0.0,
    "rain_accum_24h": 0.0,
    "pressure_min_24h": 1019.6200000000001,
    "cloud_cover": 91.0,
    "cloud_change_1h": -1.0,
    "cloud_change_3h": -2.0,
    "is_overcast": 1.0,
    "weather_code": 3.0,
    "model_predicts_precip": 0.0,
    "wc_is_thunderstorm": 0.0,
    "wc_is_rain": 0.0,
    "wc_is_drizzle": 0.0,
    "nwp_precip_severity": 0.0,
    "nwp_dry_conflict": 0.0,
    "nwp_wet_conflict": 0.0,
    "nwp_rain_amount": 0.0,
    "nwp_rain_drying": 0.0,
    "nwp_rain_confirmed": 0.0,
    "afternoon_fp_risk": 0.0,
    "nwp_rain_dry_air": 0.0,
    "nwp_rain_persistence_6h": 0.0,
    "nwp_rain_trend_3h": 0.0,
    "weather_code_change_3h": 0.0,
    "cloud_humidity_convergence": 2.884615384615387,
    "precip_trend_3h": 0.0,
    "showers": 0.0,
    "nwp_showers_fraction": 0.0,
    "et0_fao_evapotranspiration": 0.0,
    "soil_temperature_0_to_7cm": 16.7,
    "soil_air_temp_diff": 0.0799999999999983,
    "sunshine_duration": 0.0,
    "sunshine_accum_3h": 0.0,
    "wind_speed_100m": 3.1,
    "boundary_layer_shear": 2.62,
    "wind_dir_shear_100m": 90.0,
    "snowfall": 0.0,
    "nwp_lifted_index": 7.1,
    "gph_850": 1518.0,
    "gph_850_change_3h": -12.0,
    "rh_500": 81.0,
    "dry_intrusion_500": 0.0,
    "wind_700_speed": 52.4,
    "wind_700_dir": 216.0,
    "steering_onshore_700": 0.0,
    "rain_ending_signal": 0.0,
    "cloud_thickness_proxy": 0.65,
    "radiation_rain_conflict": 0.0,
    "moisture_flux_change_3h": -32.19510074483344,
    "cape": 0.0,
    "cape_change_3h": 0.0,
    "cape_diurnal_weighted": 0.0,
    "tcwv": 24.7,
    "tcwv_change_3h": 1.0,
    "tcwv_change_6h": 2.599999999999998,
    "boundary_layer_height": 30.0,
    "blh_change_3h": -5.0,
    "tcwv_blh_ratio": 49.4,
    "terrestrial_radiation": 0.0,
    "soil_moisture_28_to_100cm": 0.169,
    "soil_saturation_ratio": 0.7159763313609466,
    "tcwv_monthly_anomaly": 1.306878306878307,
    "shortwave_radiation": 0.0,
    "radar_dbz": 0.0,
    "radar_rain_rate": 0.0,
    "radar_has_echo": 0.0,
    "radar_frames_with_echo": 0.0,
    "radar_approaching": 0.0,
    "radar_max_intensity_1h": 0.0,
    "radar_nearest_echo_km": 40.0,
    "radar_max_dbz_20km": 0.0,
    "radar_coverage_20km": 0.0,
    "radar_upwind_nearest_echo_km": 40.0,
    "radar_upwind_max_dbz": 0.0,
    "radar_storm_velocity_kmh": 0.0,
    "radar_storm_velocity_ns": 0.0,
    "radar_storm_velocity_ew": 0.0,
    "radar_storm_approaching": 0.0,
    "radar_quadrant_max_dbz_N": 0.0,
    "radar_quadrant_max_dbz_E": 0.0,
    "radar_quadrant_max_dbz_S": 0.0,
    "radar_quadrant_max_dbz_W": 0.0,
    "radar_quadrant_coverage_N": 0.0,
    "radar_quadrant_coverage_E": 0.0,
    "radar_quadrant_coverage_S": 0.0,
    "radar_quadrant_coverage_W": 0.0,
    "radar_echo_bearing_sin": null,
    "radar_echo_bearing_cos": null,
    "sentinel_temp_diff": null,
    "sentinel_humidity_diff": null,
    "sentinel_precip": null,
    "sentinel_raining": 0.0,
    "local_rain_xema": null,
    "local_rain_xema_3h": null,
    "ensemble_rain_agreement": 0.25,
    "ensemble_precip_spread": 3.4,
    "ensemble_temp_spread": 0.28613807855649037,
    "ensemble_max_precip": 3.4,
    "ensemble_min_precip": 0.0,
    "ensemble_models_rain": 1.0,
    "ensemble_surprise_rain": null,
    "nwp_isolated_rain": null,
    "forecast_temp_bias": -2.5000000000000018,
    "forecast_humidity_bias": 11.0,
    "aemet_prob_precip": 0.0,
    "aemet_prob_storm": 0.0,
    "aemet_precip_today": 0.0,
    "lightning_count_30km": 0.0,
    "lightning_count_15km": 0.0,
    "lightning_nearest_km": 40.0,
    "lightning_cloud_ground": 0.0,
    "lightning_max_current_ka": 0.0,
    "lightning_approaching": 0.0,
    "lightning_has_activity": 0.0,
    "aemet_radar_dbz": 0.0,
    "aemet_radar_has_echo": 0.0,
    "aemet_radar_nearest_echo_km": 40.0,
    "aemet_radar_max_dbz_20km": 0.0,
    "aemet_radar_coverage_20km": 0.0,
    "aemet_radar_echoes_found": 0.0,
    "smc_prob_precip_1h": null,
    "smc_prob_precip_6h": null,
    "smc_precip_intensity": null,
    "orographic_forcing": 10.53657816312207,
    "frontal_passage": 0.04048009467454951,
    "convective_composite": 0.16388669239472875,
    "thermal_buildup": 2.1099973864286382e-05,
    "low_level_convergence": 0.4643076923076319,
    "dry_intrusion_700": 0.0,
    "soil_moisture_0_to_7cm": 0.121,
    "soil_moisture_7_to_28cm": 0.179,
    "soil_moisture_change_24h": null,
    "convective_inhibition": 1.0,
    "sst_med": 17.6,
    "cloud_cover_low": 54.0,
    "cloud_cover_mid": 76.0,
    "cloud_cover_high": 0.0,
    "cloud_low_fraction": 0.5934065934065934,
    "wet_bulb_temperature_2m": 13.0,
    "wet_bulb_depression": 3.620000000000001,
    "direct_radiation": 0.0,
    "diffuse_radiation": 0.0,
    "diffuse_fraction": 0.0,
    "wind_gusts_10m": 9.4,
    "gust_factor": 18.8,
    "visibility": 22280.0,
    "freezing_level_height": 3100.0
  },
  "pressure_change_3h": -1.1030769230767419,
  "top_drivers": [
    {
      "group": "Núvols",
      "icon": "☁️",
      "contribution": 0.829,
      "direction": "pluja"
    },
    {
      "group": "Models globals",
      "icon": "🌐",
      "contribution": -0.769,
      "direction": "sec"
    },
    {
      "group": "Acord entre models",
      "icon": "🤝",
      "contribution": 0.664,
      "direction": "pluja"
    },
    {
      "group": "Pluja confirmada",
      "icon": "🌧️",
      "contribution": -0.555,
      "direction": "sec"
    },
    {
      "group": "Aigua precipitable",
      "icon": "🌊",
      "contribution": 0.231,
      "direction": "pluja"
    },
    {
      "group": "Base (climatologia)",
      "icon": "📈",
      "contribution": -2.304,
      "direction": "sec"
    }
  ],
  "verification": {
    "verified_count": 1,
    "correct_count": 1,
    "wrong_count": 0,
    "skipped": 397,
    "source": "meteocardedeu",
    "lookup_hours": 48,
    "station_rows": 2569,
    "station_first_ts": "2026-05-01T02:12:00",
    "station_last_ts": "2026-05-03T02:11:00",
    "pending_total": 397,
    "accuracy": 100.0
  }
}