{
  "probability": 0.0001,
  "probability_pct": 0.0,
  "will_rain": false,
  "confidence": "Molt Baixa",
  "timestamp": "2026-03-21T11:00:50.558965",
  "conditions": {
    "temperature": "14.8",
    "humidity": 48,
    "pressure": "1014.7",
    "wind_speed": "4.8",
    "wind_dir": "SO",
    "rain_today": "0.0",
    "solar_radiation": 649
  },
  "radar": {
    "dbz": 0.0,
    "rain_rate_mmh": 0.0,
    "has_echo": false,
    "approaching": false,
    "nearest_echo_km": 30,
    "nearest_echo_compass": null,
    "max_dbz_20km": 0.0,
    "coverage_20km": 0.0,
    "upwind_nearest_echo_km": 30,
    "storm_velocity_kmh": 0.0,
    "storm_eta_min": null,
    "quadrants": {
      "max_dbz_N": 0.0,
      "max_dbz_E": 0.0,
      "max_dbz_S": 0.0,
      "max_dbz_W": 0.0,
      "coverage_N": 0.0,
      "coverage_E": 0.0,
      "coverage_S": 0.0,
      "coverage_W": 0.0
    }
  },
  "sentinel": {
    "station": "Granollers",
    "temp": null,
    "humidity": null,
    "precip": null,
    "raining": 0
  },
  "ensemble": {
    "rain_agreement": 0.0,
    "precip_spread_mm": 0.0,
    "models_rain": 0,
    "total_models": 4
  },
  "aemet": {
    "prob_precip": null,
    "prob_storm": null
  },
  "bias": {
    "temp": -0.10000000000000142,
    "humidity": -1.0
  },
  "wind_regime": {
    "level": "850hPa",
    "is_tramuntana": false,
    "is_llevantada": true,
    "is_migjorn": false,
    "is_garbi": false,
    "is_ponent": false,
    "llevantada_strength": 4.947727272727273,
    "wind_dir_change_3h": 0.0
  },
  "pressure_levels": {
    "temp_925": 7.9,
    "rh_925": 47,
    "wind_925_speed_kmh": 7.5,
    "wind_925_dir": 216,
    "wind_850_dir": 211,
    "wind_850_speed_kmh": 12.3,
    "temp_850": 2.7,
    "rh_850": 39,
    "rh_700": 27,
    "temp_700": -4.0,
    "temp_500": -20.1,
    "wind_300_speed_kmh": 54.7,
    "wind_300_dir": 285,
    "gph_300": 9153.23,
    "vt_index": 22.8,
    "tt_index": 33.03660996729198,
    "li_index": 4.167610265536307
  },
  "sst": {
    "sst_med": 14.6
  },
  "rain_gate_open": false,
  "features_used": 199,
  "threshold": 0.35260115606936415,
  "calibrated": true,
  "raw_probability": 0.0017,
  "feature_vector": {
    "hour_sin": 0.49999999999999994,
    "hour_cos": -0.8660254037844387,
    "month_sin": 1.0,
    "month_cos": 6.123233995736766e-17,
    "hours_since_sunrise": 3.133689912644983,
    "pressure_msl": 1014.9272727272728,
    "pressure_change_1h": 0.013939393939494948,
    "pressure_change_3h": 0.23393939393952223,
    "pressure_change_6h": 0.1421663442940826,
    "pressure_accel_3h": -0.24189393939377624,
    "temperature_2m": 13.245454545454544,
    "relative_humidity_2m": 55.43181818181818,
    "dew_point": 4.509447169326162,
    "dew_point_depression": 8.736007376128383,
    "humidity_change_1h": -8.390404040404043,
    "humidity_change_3h": -34.99040404040404,
    "vapour_pressure_deficit": null,
    "vpd_change_3h": null,
    "wind_speed_10m": 4.947727272727273,
    "wind_u": -3.4985715060070777,
    "wind_v": 3.4985715060070772,
    "wind_speed_change_1h": 1.7121717171717177,
    "wind_speed_change_3h": 4.841060606060607,
    "is_sea_breeze": 1.0,
    "is_migjorn": 0.0,
    "is_garbi": 0.0,
    "is_ponent": 0.0,
    "llevantada_strength": 4.947727272727273,
    "llevantada_moisture": 0.5543181818181818,
    "garbi_strength": 0.0,
    "tramuntana_strength": 0.0,
    "tramuntana_moisture": 0.0,
    "wind_dir_change_3h": 0.0,
    "temp_925": 7.9,
    "rh_925": 47.0,
    "wind_925_speed": 7.5,
    "wind_925_dir": 216.0,
    "wind_850_speed": 12.3,
    "wind_850_dir": 211.0,
    "temp_850": 2.7,
    "temp_500": -20.1,
    "rh_850": 39.0,
    "rh_700": 27.0,
    "temp_700": -4.0,
    "rh_700_change_3h": null,
    "rh_700_change_6h": null,
    "temp_850_change_3h": null,
    "wind_300_speed": 54.7,
    "wind_300_dir": 285.0,
    "gph_300": 9153.23,
    "vt_index": 22.8,
    "tt_index": 33.03660996729198,
    "li_index": 4.167610265536307,
    "li_unstable": null,
    "k_index": null,
    "moisture_flux_850": null,
    "moisture_flux_925": null,
    "theta_e_deficit": null,
    "inversion_925": null,
    "deep_layer_shear": null,
    "bulk_richardson": null,
    "jet_speed_300": null,
    "wind_shear_speed": null,
    "wind_shear_dir": null,
    "precipitation": 0.0,
    "rain_accum_3h": 0.0,
    "rain_accum_6h": 0.0,
    "rained_last_3h": 0.0,
    "cloud_cover": 0.0,
    "cloud_change_1h": 0.0,
    "cloud_change_3h": null,
    "is_overcast": 0.0,
    "weather_code": 0.0,
    "model_predicts_precip": 0.0,
    "wc_is_thunderstorm": 0.0,
    "wc_is_rain": 0.0,
    "wc_is_drizzle": 0.0,
    "nwp_dry_conflict": 0.0,
    "nwp_wet_conflict": 0.0,
    "nwp_rain_amount": 0.0,
    "nwp_rain_drying": 0.0,
    "nwp_rain_confirmed": 0.0,
    "afternoon_fp_risk": 0.0,
    "nwp_rain_dry_air": 0.0,
    "showers": 0.0,
    "nwp_showers_fraction": 0.0,
    "et0_fao_evapotranspiration": 0.32,
    "soil_temperature_0_to_7cm": null,
    "soil_air_temp_diff": null,
    "sunshine_duration": 3600.0,
    "sunshine_accum_3h": 7200.0,
    "wind_speed_100m": 7.7,
    "boundary_layer_shear": 2.752272727272727,
    "wind_dir_shear_100m": 94.0,
    "snowfall": 0.0,
    "nwp_lifted_index": null,
    "gph_850": null,
    "gph_850_change_3h": null,
    "rh_500": null,
    "dry_intrusion_500": null,
    "wind_700_speed": null,
    "wind_700_dir": null,
    "steering_onshore_700": null,
    "rain_ending_signal": null,
    "cloud_thickness_proxy": 0.0,
    "radiation_rain_conflict": 0.0,
    "moisture_flux_change_3h": null,
    "cape_change_3h": null,
    "tcwv": 6.7,
    "tcwv_change_3h": null,
    "tcwv_change_6h": null,
    "boundary_layer_height": 860.0,
    "blh_change_3h": null,
    "tcwv_blh_ratio": 0.7790697674418605,
    "terrestrial_radiation": 827.3,
    "soil_moisture_28_to_100cm": null,
    "soil_saturation_ratio": null,
    "tcwv_monthly_anomaly": 0.5234375,
    "shortwave_radiation": 580.3181818181819,
    "radar_dbz": 0.0,
    "radar_rain_rate": 0.0,
    "radar_has_echo": 0.0,
    "radar_frames_with_echo": 0.0,
    "radar_approaching": 0.0,
    "radar_max_intensity_1h": 0.0,
    "radar_nearest_echo_km": 30.0,
    "radar_max_dbz_20km": 0.0,
    "radar_coverage_20km": 0.0,
    "radar_upwind_nearest_echo_km": 30.0,
    "radar_upwind_max_dbz": 0.0,
    "radar_storm_velocity_kmh": 0.0,
    "radar_storm_approaching": 0.0,
    "radar_quadrant_max_dbz_N": 0.0,
    "radar_quadrant_max_dbz_E": 0.0,
    "radar_quadrant_max_dbz_S": 0.0,
    "radar_quadrant_max_dbz_W": 0.0,
    "radar_quadrant_coverage_N": 0.0,
    "radar_quadrant_coverage_E": 0.0,
    "radar_quadrant_coverage_S": 0.0,
    "radar_quadrant_coverage_W": 0.0,
    "radar_echo_bearing_sin": null,
    "radar_echo_bearing_cos": null,
    "sentinel_temp_diff": null,
    "sentinel_humidity_diff": null,
    "sentinel_precip": null,
    "sentinel_raining": 0.0,
    "local_rain_xema": null,
    "local_rain_xema_3h": null,
    "ensemble_rain_agreement": 0.0,
    "ensemble_precip_spread": 0.0,
    "ensemble_temp_spread": 0.5973901572674262,
    "ensemble_max_precip": 0.0,
    "ensemble_min_precip": 0.0,
    "ensemble_models_rain": 0.0,
    "forecast_temp_bias": -0.10000000000000142,
    "forecast_humidity_bias": -1.0,
    "aemet_prob_precip": null,
    "aemet_prob_storm": null,
    "aemet_precip_today": null,
    "lightning_count_30km": null,
    "lightning_count_15km": null,
    "lightning_nearest_km": null,
    "lightning_cloud_ground": null,
    "lightning_max_current_ka": null,
    "lightning_approaching": null,
    "lightning_has_activity": null,
    "aemet_radar_dbz": 0.0,
    "aemet_radar_has_echo": 0.0,
    "aemet_radar_nearest_echo_km": 30.0,
    "aemet_radar_max_dbz_20km": 0.0,
    "aemet_radar_coverage_20km": 0.0,
    "aemet_radar_echoes_found": 0.0,
    "smc_prob_precip_1h": null,
    "smc_prob_precip_6h": null,
    "smc_precip_intensity": null,
    "orographic_forcing": null,
    "frontal_passage": 0.0,
    "convective_composite": null,
    "thermal_buildup": 0.1955620258611332,
    "low_level_convergence": 0.0,
    "dry_intrusion_700": null,
    "soil_moisture_0_to_7cm": null,
    "soil_moisture_7_to_28cm": null,
    "soil_moisture_change_24h": null,
    "convective_inhibition": null,
    "sst_med": 14.6,
    "cloud_cover_low": 0.0,
    "cloud_cover_mid": 0.0,
    "cloud_cover_high": 0.0,
    "cloud_low_fraction": 0.0,
    "wet_bulb_temperature_2m": 8.8,
    "wet_bulb_depression": 4.4454545454545435,
    "direct_radiation": 537.0,
    "diffuse_radiation": 82.0,
    "diffuse_fraction": 0.13247172859450726,
    "wind_gusts_10m": 15.5,
    "gust_factor": 3.13275149288011,
    "visibility": null,
    "freezing_level_height": null
  },
  "pressure_change_3h": 0.23393939393952223
}